{
  "name": "Mason Arnold",
  "age": 18,
  "address": {
    "street": "Zija River",
    "city": "Oheraho",
    "state": "SD",
    "zip": "85388"
  },
  "contact": {
    "phone": "(806) 647-8185",
    "servicePhone": "800173476"
  },
  "birthday": "1997-01-15T13:32:44.700Z",
  "ip": "57.156.59.85",
  "foo": "bar",
  "profile": {
    "about": "Ed al dec gev irana unva to cetdewgav mel za dah irbuwpuw ulucofe fe puw fi. Ri za vumcito lojuknif hudo fu hu raikotub roakaezu delajubo amubuv pehru nuc ozomowkuf rarvic. Taus tuhuf ceg val fioj iserodid ozuim hara viz ol awso jumab wofen iskowo hocib kewlab zukzelbu. Lid neaz suisog tilehpar vibanuw ku afmoc herazohe cu degu an red.",
    "bio": "Eh lewapidi noknewa urgut nodcab telfok ig oba aso sacat loija ak haneto luwutra pi ebeabafa icina nop. Vucovge boznavik pupehniw hu inha joponi ga topo obefu ah ribsi tegil ru ro mimfo juwpuzju fofbu te. Metopupin evaju pol badmedpe nodbagtu diwu fahih wuveop ekcohma wib vi ivehumo wowkaaci vefpin biah bi arkep. Rah tokihoze gampejno lulakume giwgu hinod nozac we ensi ekhoah ronakwag lojifap ufihac ge ici dev puv az. Nizod abmobo sefnovjob lubjo apjifko lef ge cu paw enpid temitub mahuol so. Bokwes aru ni zivojbu ivowi ije kine dop kooputu tirita ofbarwe turpar hamlejjaw lujawe. Hetem ogu mama kun zoniroope hofu cil wedaci ed kasco beuko sa himahul soz opizaak zaf fi binmizhe."
  },
  "apiKey": "56356aadb03a4418ac90be78ad53d2668701a663b5f199f3c439ac17b511bb38",
  "currency": {
    "code": "OMR",
    "name": "Oman Rial"
  }
}