{
  "name": "Mathilda Casey",
  "age": 33,
  "address": {
    "street": "Urhe River",
    "city": "Ezmegur",
    "state": "NC",
    "zip": "34967"
  },
  "contact": {
    "phone": "(300) 995-3727",
    "servicePhone": "800599662"
  },
  "birthday": "1990-01-11T17:08:07.800Z",
  "ip": "155.121.105.170",
  "foo": "bar",
  "profile": {
    "about": "Co mun godera hiepoif fik roone wid nez ujden racki ovi oki wawaraab il kesa. Kib getbusbem ivavo igana lobeger fev fes naleh loz bub rapil be izi eja lemano kisze den cine. Vutit capwu ba ru lacalpal hetbizzuz pa isa doj uhmon ruf lazocrem fejuteb. Ihi naoj itmisite pebeguzu pupzizha siciapi aswi sogofro vufial ovvotur ig atkuswo dij canam jaceke pobi zadab.",
    "bio": "Waw rifu opip pigvofi mihabdom moka bofzih enebi la penpoaw ce vapawojow hutug capha ni ru wubnaloj. Luwavle deave zeem hucaini sujitvu kapopriz perar ajo julij jik fino ip kir cecsuhces wa. Nadicwe gefof kip emotaaze dip litu cowva cobmakza de lunav ico nejabo ju. Lin kisolano itoc lab lu zelu bijnu uc fa umtitta hin jatdol bobsav siz."
  },
  "apiKey": "3fca892ed858d98145c092b5a8408556c53ae9a30156e94fafb47036c6e34a09",
  "currency": {
    "code": "TZS",
    "name": "Tanzania Shilling"
  }
}